itam_assistant/__init__.py
itam_assistant/ailyapp_client.py
itam_assistant/config.py
itam_assistant/do_ai.py
itam_assistant/intent_detail.py
itam_assistant/lark_client.py
itam_assistant/logger.py
itam_assistant/openapi.py
itam_assistant/test.py
itam_assistant-0.1.18.dist-info/METADATA
itam_assistant-0.1.18.dist-info/WHEEL
itam_assistant-0.1.18.dist-info/top_level.txt
itam_assistant-0.1.18.dist-info/RECORD
