Metadata-Version: 2.4
Name: itam_assistant
Version: 0.1.18
Summary: 新增功能：打印出记录
Home-page: https://github.com/liujunmeiD/itam_assistant
Author: liujunmeiD
Author-email: 1105030421@qq.com
Classifier: Programming Language :: Python :: 3
Classifier: License :: OSI Approved :: MIT License
Classifier: Operating System :: OS Independent
Requires-Python: >=3.6
Requires-Dist: requests>=2.25.1
Requires-Dist: numpy>=1.20.0
Dynamic: author
Dynamic: author-email
Dynamic: classifier
Dynamic: description
Dynamic: description-content-type
Dynamic: home-page
Dynamic: requires-dist
Dynamic: requires-python
Dynamic: summary
